udsoncan/BaseService.py
udsoncan/Request.py
udsoncan/Response.py
udsoncan/ResponseCode.py
udsoncan/__init__.py
udsoncan/client.py
udsoncan/configs.py
udsoncan/connections.py
udsoncan/exceptions.py
udsoncan/j2534.py
udsoncan/logging.conf
udsoncan/py.typed
udsoncan/tools.py
udsoncan/typing.py
udsoncan/common/AddressAndLengthFormatIdentifier.py
udsoncan/common/Baudrate.py
udsoncan/common/CommunicationType.py
udsoncan/common/DataFormatIdentifier.py
udsoncan/common/DidCodec.py
udsoncan/common/DynamicDidDefinition.py
udsoncan/common/Filesize.py
udsoncan/common/IOControls.py
udsoncan/common/MemoryLocation.py
udsoncan/common/Routine.py
udsoncan/common/Units.py
udsoncan/common/__init__.py
udsoncan/common/dids.py
udsoncan/common/dtc.py
udsoncan/services/AccessTimingParameter.py
udsoncan/services/Authentication.py
udsoncan/services/ClearDiagnosticInformation.py
udsoncan/services/CommunicationControl.py
udsoncan/services/ControlDTCSetting.py
udsoncan/services/DiagnosticSessionControl.py
udsoncan/services/DynamicallyDefineDataIdentifier.py
udsoncan/services/ECUReset.py
udsoncan/services/InputOutputControlByIdentifier.py
udsoncan/services/LinkControl.py
udsoncan/services/ReadDTCInformation.py
udsoncan/services/ReadDataByIdentifier.py
udsoncan/services/ReadDataByPeriodicIdentifier.py
udsoncan/services/ReadMemoryByAddress.py
udsoncan/services/ReadScalingDataByIdentifier.py
udsoncan/services/RequestDownload.py
udsoncan/services/RequestFileTransfer.py
udsoncan/services/RequestTransferExit.py
udsoncan/services/RequestUpload.py
udsoncan/services/ResponseOnEvent.py
udsoncan/services/RoutineControl.py
udsoncan/services/SecuredDataTransmission.py
udsoncan/services/SecurityAccess.py
udsoncan/services/TesterPresent.py
udsoncan/services/TransferData.py
udsoncan/services/WriteDataByIdentifier.py
udsoncan/services/WriteMemoryByAddress.py
udsoncan/services/__init__.py
udsoncan-1.25.1.dist-info/licenses/LICENSE.txt
udsoncan-1.25.1.dist-info/METADATA
udsoncan-1.25.1.dist-info/WHEEL
udsoncan-1.25.1.dist-info/top_level.txt
udsoncan-1.25.1.dist-info/RECORD
