Metadata-Version: 2.4
Name: udsoncan
Version: 1.25.1
Summary: Implementation of the Unified Diagnostic Service (UDS) protocol (ISO-14229) used in the automotive industry.
Home-page: https://github.com/pylessard/python-udsoncan
Download-URL: https://github.com/pylessard/python-udsoncan/archive/v1.25.1.tar.gz
Author: Pier-Yves Lessard
Author-email: py.lessard@gmail.com
License: MIT
Keywords: uds,14229,iso-14229,diagnostic,automotive
Classifier: Programming Language :: Python
Classifier: Programming Language :: Python :: 3
Classifier: Development Status :: 4 - Beta
Classifier: Operating System :: POSIX :: Linux
Classifier: Intended Audience :: Developers
Classifier: License :: OSI Approved :: MIT License
Classifier: Topic :: Scientific/Engineering :: Interface Engine/Protocol Translator
Requires-Python: >=3.7
License-File: LICENSE.txt
Provides-Extra: test
Requires-Dist: mypy; extra == "test"
Requires-Dist: coverage; extra == "test"
Provides-Extra: dev
Requires-Dist: mypy; extra == "dev"
Requires-Dist: ipdb; extra == "dev"
Requires-Dist: autopep8; extra == "dev"
Requires-Dist: coverage; extra == "dev"
Dynamic: author
Dynamic: author-email
Dynamic: classifier
Dynamic: description
Dynamic: download-url
Dynamic: home-page
Dynamic: keywords
Dynamic: license
Dynamic: license-file
Dynamic: provides-extra
Dynamic: requires-python
Dynamic: summary
